{"data": [{"kind": "youtube#searchResult", "etag": "O4tDFp0WdC4X65NCxBzU8_Dqles", "id": {"kind": "youtube#video", "videoId": "aOVroNWY0KM"}, "snippet": {"publishedAt": "2026-04-10T10:30:00Z", "channelId": "UCG8FlsZgr7k9cZKZ3AWDU4A", "title": "@MotorcycleTrails going fast on the Proloy EV dirt bike from @ProjectSR  | Nikhil Sood", "description": "POV action from trail rides around Pune \u2014 raw helmet-cam action and real trail moments. Riding Gear Partner - \u2068@store4riders ...", "thumbnails": {"default": {"url": "https://i.ytimg.com/vi/aOVroNWY0KM/default.jpg", "width": 120, "height": 90}, "medium": {"url": "https://i.ytimg.com/vi/aOVroNWY0KM/mqdefault.jpg", "width": 320, "height": 180}, "high": {"url": "https://i.ytimg.com/vi/aOVroNWY0KM/hqdefault.jpg", "width": 480, "height": 360}}, "channelTitle": "Motorcycle Trails RAW", "liveBroadcastContent": "none", "publishTime": "2026-04-10T10:30:00Z"}}, {"kind": "youtube#searchResult", "etag": "VNPtzk4XhdlA9LUiJ4_J0xK6KEw", "id": {"kind": "youtube#video", "videoId": "jib5PBggzng"}, "snippet": {"publishedAt": "2026-04-10T07:56:02Z", "channelId": "UCsgixH07O_IYmm-CHjVHFxA", "title": "New 2026 Nissan Rogue Sarasota, FL #4331943", "description": "http://www.gettelnissan.com/ Call or visit for a test drive of this vehicle today! Phone: 877-219-6746 Year: 2026 Make: Nissan ...", "thumbnails": {"default": {"url": "https://i.ytimg.com/vi/jib5PBggzng/default.jpg", "width": 120, "height": 90}, "medium": {"url": "https://i.ytimg.com/vi/jib5PBggzng/mqdefault.jpg", "width": 320, "height": 180}, "high": {"url": "https://i.ytimg.com/vi/jib5PBggzng/hqdefault.jpg", "width": 480, "height": 360}}, "channelTitle": "Gettel Nissan", "liveBroadcastContent": "none", "publishTime": "2026-04-10T07:56:02Z"}}, {"kind": "youtube#searchResult", "etag": "LSJRHJWsxCW5fmLBuzmOdPNC12U", "id": {"kind": "youtube#video", "videoId": "pRbWqSf9oME"}, "snippet": {"publishedAt": "2026-04-10T06:19:50Z", "channelId": "UCGcaXp4ZnWgpPNp4QrdpU-A", "title": "Vehicle Engg- Testing of Suspension system &amp; Air Suspension System 33", "description": "Title: Testing of Suspension System | Vehicle Engineering Explained Prompt (for video creation): Create an educational ...", "thumbnails": {"default": {"url": "https://i.ytimg.com/vi/pRbWqSf9oME/default.jpg", "width": 120, "height": 90}, "medium": {"url": "https://i.ytimg.com/vi/pRbWqSf9oME/mqdefault.jpg", "width": 320, "height": 180}, "high": {"url": "https://i.ytimg.com/vi/pRbWqSf9oME/hqdefault.jpg", "width": 480, "height": 360}}, "channelTitle": "AGS MECH TECH", "liveBroadcastContent": "none", "publishTime": "2026-04-10T06:19:50Z"}}, {"kind": "youtube#searchResult", "etag": "Zr7W3prkLQ80I3MC3TZ-yqkSguU", "id": {"kind": "youtube#video", "videoId": "-jdZnRSOaXs"}, "snippet": {"publishedAt": "2026-04-10T05:58:26Z", "channelId": "UCRWc4nqeZD9GB7pHC6KDGnA", "title": "Tragic Landslide in Shivamogga: Three Laborers Lose Lives During Road Work | HEADLINES URDU", "description": "A devastating landslide occurred in the Hulikal Ghat area of Shivamogga, Karnataka, during ongoing road construction. According ...", "thumbnails": {"default": {"url": "https://i.ytimg.com/vi/-jdZnRSOaXs/default.jpg", "width": 120, "height": 90}, "medium": {"url": "https://i.ytimg.com/vi/-jdZnRSOaXs/mqdefault.jpg", "width": 320, "height": 180}, "high": {"url": "https://i.ytimg.com/vi/-jdZnRSOaXs/hqdefault.jpg", "width": 480, "height": 360}}, "channelTitle": "Munsif TV LIVE", "liveBroadcastContent": "none", "publishTime": "2026-04-10T05:58:26Z"}}, {"kind": "youtube#searchResult", "etag": "V8z_ZJuKbTy9jdF8Csr33oP3HBo", "id": {"kind": "youtube#video", "videoId": "7V2Bt2SXXTg"}, "snippet": {"publishedAt": "2026-04-10T10:20:09Z", "channelId": "UCXoEW19895cLazOGJMSlkEA", "title": "\u0926\u093e\u0939\u094b\u0926 : \u092c\u0921\u093c\u093e \u0939\u093e\u0926\u0938\u093e, \u0928\u0947\u0936\u0928\u0932 \u0939\u093e\u0908\u0935\u0947 \u092a\u0930 \u091f\u094d\u0930\u0915 \u092a\u0932\u091f\u093e, \u091a\u093e\u0932\u0915 \u0918\u093e\u092f\u0932", "description": "\u0926\u093e\u0939\u094b\u0926-\u0905\u0932\u0940\u0930\u093e\u091c\u092a\u0941\u0930 \u0928\u0947\u0936\u0928\u0932 \u0939\u093e\u0908\u0935\u0947 \u092a\u0930 \u0917\u0930\u092c\u093e\u0921\u093c\u093e \u0915\u0947 \u092a\u093e\u091f\u093f\u092f\u093e\u091c\u094b\u0932 \u092a\u0941\u0932 \u092a\u0930 \u092c\u0921\u093c\u093e ...", "thumbnails": {"default": {"url": "https://i.ytimg.com/vi/7V2Bt2SXXTg/default.jpg", "width": 120, "height": 90}, "medium": {"url": "https://i.ytimg.com/vi/7V2Bt2SXXTg/mqdefault.jpg", "width": 320, "height": 180}, "high": {"url": "https://i.ytimg.com/vi/7V2Bt2SXXTg/hqdefault.jpg", "width": 480, "height": 360}}, "channelTitle": "BBC RAJASTHAN", "liveBroadcastContent": "none", "publishTime": "2026-04-10T10:20:09Z"}}, {"kind": "youtube#searchResult", "etag": "krbaGHmOAUIS2wXYMcIGEyTyPZg", "id": {"kind": "youtube#video", "videoId": "ogNsnRe8C94"}, "snippet": {"publishedAt": "2026-04-10T07:30:00Z", "channelId": "UCRhn9m9IoXxi58ixl3zKrxA", "title": "\u0412\u0438\u043a\u0442\u043e\u0440\u0438\u043d\u0430 \u043d\u0430 \u0437\u043d\u0430\u043d\u0438\u0435 \u0434\u043e\u0440\u043e\u0436\u043d\u044b\u0445 \u0437\u043d\u0430\u043a\u043e\u0432. \u0413\u043e\u0442\u043e\u0432\u0438\u043c\u0441\u044f \u043a \u044d\u043a\u0437\u0430\u043c\u0435\u043d\u0443 \u0432 \u0413\u0418\u0411\u0414\u0414 (\u0441\u0441\u044b\u043b\u043a\u0430 \u0432 \u043f\u0440\u043e\u0444\u0438\u043b\u0435) #\u0432\u043e\u0436\u0434\u0435\u043d\u0438\u0435#\u043f\u0434\u0434", "description": "\u041f\u043e\u0434\u0433\u043e\u0442\u043e\u0432\u043a\u0430 \u043a \u044d\u043a\u0437\u0430\u043c\u0435\u043d\u0443 \u0432 \u0413\u0418\u0411\u0414\u0414 (\u0441\u0441\u044b\u043b\u043a\u0430 \u0432 \u043f\u0440\u043e\u0444\u0438\u043b\u0435 \u043a\u0430\u043d\u0430\u043b\u0430) \u0411\u043e\u043b\u0435\u0435 5500 \u0443\u0447\u0435\u043d\u0438\u043a\u043e\u0432 \u0441\u0434\u0430\u043b\u0438 \u044d\u043a\u0437\u0430\u043c\u0435\u043d \u0441 \u043f\u0435\u0440\u0432\u043e\u0433\u043e \u0440\u0430\u0437\u0430!", "thumbnails": {"default": {"url": "https://i.ytimg.com/vi/ogNsnRe8C94/default.jpg", "width": 120, "height": 90}, "medium": {"url": "https://i.ytimg.com/vi/ogNsnRe8C94/mqdefault.jpg", "width": 320, "height": 180}, "high": {"url": "https://i.ytimg.com/vi/ogNsnRe8C94/hqdefault.jpg", "width": 480, "height": 360}}, "channelTitle": "\u041e\u043d\u043b\u0430\u0439\u043d \u041f\u0414\u0414 \u043e\u0442 \u0420\u0430\u043c\u0438\u043b\u044f \u041a\u0430\u043f\u043f\u0430\u0441\u043e\u0432\u0430", "liveBroadcastContent": "none", "publishTime": "2026-04-10T07:30:00Z"}}, {"kind": "youtube#searchResult", "etag": "d_u2ej7YVdAA_CXJadp_02yftWA", "id": {"kind": "youtube#video", "videoId": "kBFS1B6lKf0"}, "snippet": {"publishedAt": "2026-04-10T08:30:26Z", "channelId": "UCNSiRrXZsuLTJQytwFCbR2g", "title": "\u6709\u7a7a\u8c03\u7684\u751f\u6d3b\u592a\u597d\u4e86\u5c31\u662f\u6bcf\u6b21\u5f00\u7a7a\u8c03\u90fd\u60f3\u8d77\u4e86\u5168\u987a\u54e5\uff0c\u54c8\u54c8\u54c8#\u7a77\u6e38 #\u81ea\u9a7e\u6e38", "description": "\u6709\u7a7a\u8c03\u7684\u751f\u6d3b\u592a\u597d\u4e86\u5c31\u662f\u6bcf\u6b21\u5f00\u7a7a\u8c03\u90fd\u60f3\u8d77\u4e86\u5168\u987a\u54e5\uff0c\u54c8\u54c8\u54c8#\u7a77\u6e38#\u81ea\u9a7e\u6e38\u5c0f\u8d3e\u6f02\u6d41\u8bb0\u5b98\u65b9\u9891\u9053\u6765\u81ea\u6cb3\u5357\u7701\u65b0\u4e61\u5e02\u5c01\u4e18\u53bf\uff0c\u4e00\u4eba\u4e00\u8f66 ...", "thumbnails": {"default": {"url": "https://i.ytimg.com/vi/kBFS1B6lKf0/default.jpg", "width": 120, "height": 90}, "medium": {"url": "https://i.ytimg.com/vi/kBFS1B6lKf0/mqdefault.jpg", "width": 320, "height": 180}, "high": {"url": "https://i.ytimg.com/vi/kBFS1B6lKf0/hqdefault.jpg", "width": 480, "height": 360}}, "channelTitle": "\u5c0f\u8d3e\u6f02\u6d41\u8bb0", "liveBroadcastContent": "none", "publishTime": "2026-04-10T08:30:26Z"}}, {"kind": "youtube#searchResult", "etag": "Dkv2rWrZ1RcxAKTf35vzL099GxA", "id": {"kind": "youtube#video", "videoId": "GgkXCDQ00hc"}, "snippet": {"publishedAt": "2026-04-10T09:26:07Z", "channelId": "UCri5Ju8uqRxIAwIQp8FsBYQ", "title": "DL-HR \u0935\u093e\u0939\u0928\u094b\u0902 \u092a\u0930 \u092e\u0902\u0924\u094d\u0930\u0940 \u0938\u0916\u094d\u0924 #parvatsankalpnews #pushkarsinghdhami", "description": "\u0909\u0924\u094d\u0924\u0930\u093e\u0916\u0902\u0921 \u092e\u0947\u0902 \u092c\u093e\u0939\u0930\u0940 \u0930\u093e\u091c\u094d\u092f\u094b\u0902 \u0935\u093f\u0936\u0947\u0937\u0915\u0930 DL \u0914\u0930 HR \u0928\u0902\u092c\u0930 \u0915\u0940 \u0917\u093e\u0921\u093c\u093f\u092f\u094b\u0902 \u0915\u094b ...", "thumbnails": {"default": {"url": "https://i.ytimg.com/vi/GgkXCDQ00hc/default.jpg", "width": 120, "height": 90}, "medium": {"url": "https://i.ytimg.com/vi/GgkXCDQ00hc/mqdefault.jpg", "width": 320, "height": 180}, "high": {"url": "https://i.ytimg.com/vi/GgkXCDQ00hc/hqdefault.jpg", "width": 480, "height": 360}}, "channelTitle": "Parvat Sankalp ", "liveBroadcastContent": "none", "publishTime": "2026-04-10T09:26:07Z"}}, {"kind": "youtube#searchResult", "etag": "PCycXVYETT_LS-NauzqYB8_cldg", "id": {"kind": "youtube#video", "videoId": "GkTEZ6NQy1U"}, "snippet": {"publishedAt": "2026-04-10T06:40:28Z", "channelId": "UC6kSUECB0uANueps12UvMlA", "title": "\u0905\u092c \u0939\u093e\u0926\u0938\u0947 \u092e\u0947\u0902 \u092e\u0926\u0926 \u0915\u0930\u0928\u0947 \u092a\u0930 \u092e\u093f\u0932\u0947\u0917\u093e \u20b925,000! \u0938\u0930\u0915\u093e\u0930 \u0915\u0940 \u092c\u0921\u093c\u0940 \u092a\u0939\u0932", "description": "\u0938\u0921\u093c\u0915 \u0939\u093e\u0926\u0938\u094b\u0902 \u092e\u0947\u0902 \u0918\u093e\u092f\u0932 \u0932\u094b\u0917\u094b\u0902 \u0915\u0940 \u092e\u0926\u0926 \u0915\u0930\u0928\u0947 \u0935\u093e\u0932\u094b\u0902 \u0915\u0947 \u0932\u093f\u090f \u0938\u0930\u0915\u093e\u0930 \u0928\u0947 \u0928\u0908 \u092a\u0939\u0932 ...", "thumbnails": {"default": {"url": "https://i.ytimg.com/vi/GkTEZ6NQy1U/default.jpg", "width": 120, "height": 90}, "medium": {"url": "https://i.ytimg.com/vi/GkTEZ6NQy1U/mqdefault.jpg", "width": 320, "height": 180}, "high": {"url": "https://i.ytimg.com/vi/GkTEZ6NQy1U/hqdefault.jpg", "width": 480, "height": 360}}, "channelTitle": "Rashtriyahindimaildigital", "liveBroadcastContent": "none", "publishTime": "2026-04-10T06:40:28Z"}}, {"kind": "youtube#searchResult", "etag": "h5WpkPEyt4m0TwlAVCvpyBECFK0", "id": {"kind": "youtube#video", "videoId": "aKu7M9G9asg"}, "snippet": {"publishedAt": "2026-04-10T07:14:04Z", "channelId": "UCwPswLpxE6iUB-jo03WdPGA", "title": "#shorts rider ktm reaction\ud83d\udc40superbike\ud83d\ude31 #kawasaki #yamaha #rider #crash #modified #popular #r15 #ktm", "description": "shorts rider ktm reaction  superbike #kawasaki #yamaha #rider #crash #modified #popular #r15 #ktm #rc \u201cDisclaimer: All ...", "thumbnails": {"default": {"url": "https://i.ytimg.com/vi/aKu7M9G9asg/default.jpg", "width": 120, "height": 90}, "medium": {"url": "https://i.ytimg.com/vi/aKu7M9G9asg/mqdefault.jpg", "width": 320, "height": 180}, "high": {"url": "https://i.ytimg.com/vi/aKu7M9G9asg/hqdefault.jpg", "width": 480, "height": 360}}, "channelTitle": "sachin live", "liveBroadcastContent": "none", "publishTime": "2026-04-10T07:14:04Z"}}, {"kind": "youtube#searchResult", "etag": "Wfo8h5Oca_oS7DHdum_AlfMdjsc", "id": {"kind": "youtube#video", "videoId": "0EcELEDZD0Q"}, "snippet": {"publishedAt": "2026-04-10T05:51:43Z", "channelId": "UC3OahOhNGvj2zo6QWKzi2ew", "title": "Ranchi accident:\u201cTruck Crashes Into Barricade on Ratu Road Flyover in Ranchi\u201d", "description": "A high-speed truck crashed into the barricade on Ranchi's Ratu Road flyover late at night, reportedly around 3 AM, causing ...", "thumbnails": {"default": {"url": "https://i.ytimg.com/vi/0EcELEDZD0Q/default.jpg", "width": 120, "height": 90}, "medium": {"url": "https://i.ytimg.com/vi/0EcELEDZD0Q/mqdefault.jpg", "width": 320, "height": 180}, "high": {"url": "https://i.ytimg.com/vi/0EcELEDZD0Q/hqdefault.jpg", "width": 480, "height": 360}}, "channelTitle": "Inspiring Jharkhand", "liveBroadcastContent": "none", "publishTime": "2026-04-10T05:51:43Z"}}, {"kind": "youtube#searchResult", "etag": "gOPCy4V4Fefm67y6teceSQVJT1w", "id": {"kind": "youtube#video", "videoId": "lUfklUkqAwI"}, "snippet": {"publishedAt": "2026-04-10T05:54:22Z", "channelId": "UCVPtkb4K4txOZdVbtmyoEVA", "title": "2021 Jeep Compass Trailhawk Kenner, Metairie, New Orleans, Harvey, River Ridge, LA", "description": "Toyota of Kenner is located at 2460 Veterans Memorial Blvd, Kenner, LA 70062 and can be reached by phone via (504) 226-5979 ...", "thumbnails": {"default": {"url": "https://i.ytimg.com/vi/lUfklUkqAwI/default.jpg", "width": 120, "height": 90}, "medium": {"url": "https://i.ytimg.com/vi/lUfklUkqAwI/mqdefault.jpg", "width": 320, "height": 180}, "high": {"url": "https://i.ytimg.com/vi/lUfklUkqAwI/hqdefault.jpg", "width": 480, "height": 360}}, "channelTitle": "Toyota of Kenner", "liveBroadcastContent": "none", "publishTime": "2026-04-10T05:54:22Z"}}, {"kind": "youtube#searchResult", "etag": "2gDOJwp9_AI69-PemVhxXAcdJDY", "id": {"kind": "youtube#video", "videoId": "g2Ig40embls"}, "snippet": {"publishedAt": "2026-04-10T06:15:02Z", "channelId": "UCQPR1AA1hpiHCiJ0Gw7KqCA", "title": "medak church #shorts #viral #youtubeshorts #medakchurch #lebiyasingh", "description": "Disclaimer: All videos on this channel are created for educational and entertainment purposes only. We do not promote or ...", "thumbnails": {"default": {"url": "https://i.ytimg.com/vi/g2Ig40embls/default.jpg", "width": 120, "height": 90}, "medium": {"url": "https://i.ytimg.com/vi/g2Ig40embls/mqdefault.jpg", "width": 320, "height": 180}, "high": {"url": "https://i.ytimg.com/vi/g2Ig40embls/hqdefault.jpg", "width": 480, "height": 360}}, "channelTitle": "LEBIYA SINGH ", "liveBroadcastContent": "none", "publishTime": "2026-04-10T06:15:02Z"}}, {"kind": "youtube#searchResult", "etag": "0negpHsMccSm8EVOTiKVxNnSi7Q", "id": {"kind": "youtube#video", "videoId": "e_hLhSMNMuk"}, "snippet": {"publishedAt": "2026-04-10T07:25:33Z", "channelId": "UCwGtNAVEB_naSWx7cq5aBQw", "title": "THIKA INDUSTRIAL SMART CITY", "description": "THIKA SMART CITY \u2013 The Rise of Kenya's Next Industrial Powerhouse Thika is on the brink of a historic transformation and this ...", "thumbnails": {"default": {"url": "https://i.ytimg.com/vi/e_hLhSMNMuk/default.jpg", "width": 120, "height": 90}, "medium": {"url": "https://i.ytimg.com/vi/e_hLhSMNMuk/mqdefault.jpg", "width": 320, "height": 180}, "high": {"url": "https://i.ytimg.com/vi/e_hLhSMNMuk/hqdefault.jpg", "width": 480, "height": 360}}, "channelTitle": "Kimani Wamatangi ", "liveBroadcastContent": "none", "publishTime": "2026-04-10T07:25:33Z"}}, {"kind": "youtube#searchResult", "etag": "L0Yq9772xTS0dBl9hx4bebgCGeE", "id": {"kind": "youtube#video", "videoId": "ECHpYT1jRyQ"}, "snippet": {"publishedAt": "2026-04-10T06:19:19Z", "channelId": "UC40FpvstQZo6Rkgc3MLgFNw", "title": "This is why you ALWAYS use a dashcam... \ud83e\udd2f #pov #dashcam", "description": "Dashcam footage proves that you can never be too careful on the road. From unexpected merges to high-speed close calls, these ...", "thumbnails": {"default": {"url": "https://i.ytimg.com/vi/ECHpYT1jRyQ/default.jpg", "width": 120, "height": 90}, "medium": {"url": "https://i.ytimg.com/vi/ECHpYT1jRyQ/mqdefault.jpg", "width": 320, "height": 180}, "high": {"url": "https://i.ytimg.com/vi/ECHpYT1jRyQ/hqdefault.jpg", "width": 480, "height": 360}}, "channelTitle": "Apex Drive POV \ud83d\udd25", "liveBroadcastContent": "none", "publishTime": "2026-04-10T06:19:19Z"}}, {"kind": "youtube#searchResult", "etag": "u_aMT8uXkObK_Zv0WGggbXIV-0s", "id": {"kind": "youtube#video", "videoId": "0yC2zlf2jps"}, "snippet": {"publishedAt": "2026-04-10T08:31:38Z", "channelId": "UCWxS911aAr0gp_KPHdsMIGg", "title": "Highway Par Dangerous Overtake!", "description": "Highway par ek chhoti si galti kitni badi ho sakti hai, ye is video me clearly dikhta hai Driver high speed me tha aur overtake karte ...", "thumbnails": {"default": {"url": "https://i.ytimg.com/vi/0yC2zlf2jps/default.jpg", "width": 120, "height": 90}, "medium": {"url": "https://i.ytimg.com/vi/0yC2zlf2jps/mqdefault.jpg", "width": 320, "height": 180}, "high": {"url": "https://i.ytimg.com/vi/0yC2zlf2jps/hqdefault.jpg", "width": 480, "height": 360}}, "channelTitle": "science factory", "liveBroadcastContent": "none", "publishTime": "2026-04-10T08:31:38Z"}}, {"kind": "youtube#searchResult", "etag": "fnyKi9QikkRufMrjt1DuqwPc1gw", "id": {"kind": "youtube#video", "videoId": "I9wMasgMlSA"}, "snippet": {"publishedAt": "2026-04-10T09:44:04Z", "channelId": "UC1bOnirKbs1oQZQIYRa6Kkg", "title": "\ud835\uddd6\ud835\ude02\ud835\ude01\ud835\uddf2 \ud835\uddda\ud835\uddf6\ud835\uddff\ud835\uddf9 \ud835\uddd6\ud835\uddf5\ud835\ude02\ud835\uddfb\ud835\uddfb\ud835\uddf6 \ud835\udde6\ud835\ude01\ud835\ude02\ud835\uddf0\ud835\uddf8 \ud835\uddf6\ud835\uddfb \ud835\uddd6\ud835\uddee\ud835\uddff \ud83d\ude02\ud83d\udca5\ud83e\udd2f#motovlog #shorts #bike #rider #youtubeshorts #viral #girl #car", "description": "Cute Girl Chunni Stuck in Car #motovlog #shorts #bike #rider #youtubeshorts #viral #girl #car ...", "thumbnails": {"default": {"url": "https://i.ytimg.com/vi/I9wMasgMlSA/default.jpg", "width": 120, "height": 90}, "medium": {"url": "https://i.ytimg.com/vi/I9wMasgMlSA/mqdefault.jpg", "width": 320, "height": 180}, "high": {"url": "https://i.ytimg.com/vi/I9wMasgMlSA/hqdefault.jpg", "width": 480, "height": 360}}, "channelTitle": "Ride With Gulshan ", "liveBroadcastContent": "none", "publishTime": "2026-04-10T09:44:04Z"}}, {"kind": "youtube#searchResult", "etag": "XnAaVnJfGhzrlVVMt3EVtVuE4lc", "id": {"kind": "youtube#video", "videoId": "x9QEPosVWhk"}, "snippet": {"publishedAt": "2026-04-10T10:37:35Z", "channelId": "UCde9NTRt_SB2DaUWGgP5fOA", "title": "\u0905\u0932\u0940\u0917\u0922\u093c \u092e\u0947\u0902 \u092c\u093e\u0907\u0915 \u0938\u094d\u091f\u0902\u091f \u0915\u0947 \u0926\u094c\u0930\u093e\u0928 \u0905\u091a\u093e\u0928\u0915 \u0939\u0941\u0906 \u0910\u0938\u093e \u0939\u093e\u0926\u0938\u093e \u0915\u093f \u0926\u0947\u0916\u0924\u0947 \u0939\u0940 \u0938\u092c \u0926\u0902\u0917 \u0930\u0939 \u0917\u090f!", "description": "\u0909\u0924\u094d\u0924\u0930 \u092a\u094d\u0930\u0926\u0947\u0936 \u0915\u0947 \u0905\u0932\u0940\u0917\u0922\u093c \u0938\u0947 \u090f\u0915 \u0939\u0948\u0930\u093e\u0928 \u0915\u0930\u0928\u0947 \u0935\u093e\u0932\u093e \u0935\u0940\u0921\u093f\u092f\u094b \u0938\u093e\u092e\u0928\u0947 \u0906\u092f\u093e \u0939\u0948 ...", "thumbnails": {"default": {"url": "https://i.ytimg.com/vi/x9QEPosVWhk/default.jpg", "width": 120, "height": 90}, "medium": {"url": "https://i.ytimg.com/vi/x9QEPosVWhk/mqdefault.jpg", "width": 320, "height": 180}, "high": {"url": "https://i.ytimg.com/vi/x9QEPosVWhk/hqdefault.jpg", "width": 480, "height": 360}}, "channelTitle": "Shukrawaar Digital", "liveBroadcastContent": "none", "publishTime": "2026-04-10T10:37:35Z"}}, {"kind": "youtube#searchResult", "etag": "5sSbC4Ir6hmzsxTsp5SRwDIHypE", "id": {"kind": "youtube#video", "videoId": "l8G0IN4VJks"}, "snippet": {"publishedAt": "2026-04-10T09:01:10Z", "channelId": "UCaJh-vUSk73t2aF5_lRaXqg", "title": "New 2026 RAV4 Woodland 2.0\u2013 China&#39;s Best-Kept Secret #RAV4 #Woodland #ToyotaSUV", "description": "The 2026 Toyota RAV4 Woodland is finally here, bringing a bold new design, upgraded hybrid performance, advanced off-road ...", "thumbnails": {"default": {"url": "https://i.ytimg.com/vi/l8G0IN4VJks/default.jpg", "width": 120, "height": 90}, "medium": {"url": "https://i.ytimg.com/vi/l8G0IN4VJks/mqdefault.jpg", "width": 320, "height": 180}, "high": {"url": "https://i.ytimg.com/vi/l8G0IN4VJks/hqdefault.jpg", "width": 480, "height": 360}}, "channelTitle": "Auto Premium Global", "liveBroadcastContent": "none", "publishTime": "2026-04-10T09:01:10Z"}}, {"kind": "youtube#searchResult", "etag": "Qr6pQWu69JrOlL7ujlo_xY3P1vQ", "id": {"kind": "youtube#video", "videoId": "lPZvw0eQi1Y"}, "snippet": {"publishedAt": "2026-04-10T08:25:00Z", "channelId": "UCSyFFWq_MG-ioRSyCY6bbQA", "title": "MP \u092e\u0947\u0902 15 \u0938\u093e\u0932 \u092a\u0941\u0930\u093e\u0928\u0940 \u092c\u0938\u0947\u0902 \u092c\u0902\u0926 \u0939\u093e\u0908\u0915\u094b\u0930\u094d\u091f \u0928\u0947 \u0938\u0930\u0915\u093e\u0930 \u0915\u0947 \u092b\u0948\u0938\u0932\u0947 \u0915\u094b \u0926\u0940 \u092e\u0902\u091c\u0942\u0930\u0940", "description": "\u092e\u0927\u094d\u092f\u092a\u094d\u0930\u0926\u0947\u0936 \u092e\u0947\u0902 15 \u0938\u093e\u0932 \u0938\u0947 \u0905\u0927\u093f\u0915 \u092a\u0941\u0930\u093e\u0928\u0940 \u0915\u092e\u0930\u094d\u0936\u093f\u092f\u0932 \u092c\u0938\u094b\u0902 \u0915\u094b \u0939\u091f\u093e\u0928\u0947 \u0915\u0947 \u0930\u093e\u091c\u094d\u092f ...", "thumbnails": {"default": {"url": "https://i.ytimg.com/vi/lPZvw0eQi1Y/default.jpg", "width": 120, "height": 90}, "medium": {"url": "https://i.ytimg.com/vi/lPZvw0eQi1Y/mqdefault.jpg", "width": 320, "height": 180}, "high": {"url": "https://i.ytimg.com/vi/lPZvw0eQi1Y/hqdefault.jpg", "width": 480, "height": 360}}, "channelTitle": "News Livemp", "liveBroadcastContent": "none", "publishTime": "2026-04-10T08:25:00Z"}}, {"kind": "youtube#searchResult", "etag": "3JGhqCgI62Dp7sW4S9AJFxK-UyI", "id": {"kind": "youtube#video", "videoId": "EXfZAUPZ1_c"}, "snippet": {"publishedAt": "2026-04-10T07:40:13Z", "channelId": "UCxLCUT4vOUSaY2QG_f2rjmg", "title": "Oznakuj auto po zdarzeniu! Noc\u0105 to ratuje \u017cycie \u26a0\ufe0f #bezpiecze\u0144stwo #droga #polscykierowcy", "description": "Po zdarzeniu na drodze liczy si\u0119 ka\u017cda sekunda. W\u0142a\u015bciwe oznakowanie pojazdu \u2013 szczeg\u00f3lnie noc\u0105 \u2013 daje innym kierowcom ...", "thumbnails": {"default": {"url": "https://i.ytimg.com/vi/EXfZAUPZ1_c/default.jpg", "width": 120, "height": 90}, "medium": {"url": "https://i.ytimg.com/vi/EXfZAUPZ1_c/mqdefault.jpg", "width": 320, "height": 180}, "high": {"url": "https://i.ytimg.com/vi/EXfZAUPZ1_c/hqdefault.jpg", "width": 480, "height": 360}}, "channelTitle": "Polscy Kierowcy", "liveBroadcastContent": "none", "publishTime": "2026-04-10T07:40:13Z"}}, {"kind": "youtube#searchResult", "etag": "EBuem2EuED2oaL7XCIFpjXmNoAs", "id": {"kind": "youtube#video", "videoId": "yesdmdOIEwQ"}, "snippet": {"publishedAt": "2026-04-10T10:02:58Z", "channelId": "UCd4PHAqxIhM7Q-PllLA1dCQ", "title": "\u201c23-Year-Old Gone\u2026 But Where Is Justice? \ud83d\udc94", "description": "A 23-year-old woman lost her life in a late-night road accident in Goa, raising serious questions about accountability and justice.", "thumbnails": {"default": {"url": "https://i.ytimg.com/vi/yesdmdOIEwQ/default.jpg", "width": 120, "height": 90}, "medium": {"url": "https://i.ytimg.com/vi/yesdmdOIEwQ/mqdefault.jpg", "width": 320, "height": 180}, "high": {"url": "https://i.ytimg.com/vi/yesdmdOIEwQ/hqdefault.jpg", "width": 480, "height": 360}}, "channelTitle": "Goa Today 24x7 News", "liveBroadcastContent": "none", "publishTime": "2026-04-10T10:02:58Z"}}, {"kind": "youtube#searchResult", "etag": "IsDDjzpu7N-fjZ2Nfbq9MYjb-bs", "id": {"kind": "youtube#video", "videoId": "REPoztWv9Zc"}, "snippet": {"publishedAt": "2026-04-10T10:37:16Z", "channelId": "UCDYBmAHNd6Uf8pXHD1gOPfg", "title": "Taj Institute of HSE Website", "description": "Welcome to Taj Institute of HSE \u2013 Health, Safety, Environment & Professional Education Hub | Rawalpindi, Pakistan We are a ...", "thumbnails": {"default": {"url": "https://i.ytimg.com/vi/REPoztWv9Zc/default.jpg", "width": 120, "height": 90}, "medium": {"url": "https://i.ytimg.com/vi/REPoztWv9Zc/mqdefault.jpg", "width": 320, "height": 180}, "high": {"url": "https://i.ytimg.com/vi/REPoztWv9Zc/hqdefault.jpg", "width": 480, "height": 360}}, "channelTitle": "Taj Institute of HSE", "liveBroadcastContent": "none", "publishTime": "2026-04-10T10:37:16Z"}}, {"kind": "youtube#searchResult", "etag": "32mpJX6CTDM6aHo3oFRdTr--ecY", "id": {"kind": "youtube#video", "videoId": "8eo3pl36tqU"}, "snippet": {"publishedAt": "2026-04-10T07:00:08Z", "channelId": "UCsnLHHJifOw27mWjBl27o6A", "title": "Top 5 Modified Jac T9 Hunter In Pakistan \ud83d\udd252026 #automobile #modified #jact9", "description": "Introducing the JAC T9 Hunter \u2014 a powerful and aggressive pickup built for both luxury and off-road performance. With a 2.0L ...", "thumbnails": {"default": {"url": "https://i.ytimg.com/vi/8eo3pl36tqU/default.jpg", "width": 120, "height": 90}, "medium": {"url": "https://i.ytimg.com/vi/8eo3pl36tqU/mqdefault.jpg", "width": 320, "height": 180}, "high": {"url": "https://i.ytimg.com/vi/8eo3pl36tqU/hqdefault.jpg", "width": 480, "height": 360}}, "channelTitle": "TORQIFY", "liveBroadcastContent": "none", "publishTime": "2026-04-10T07:00:08Z"}}, {"kind": "youtube#searchResult", "etag": "obZGB1x4soik9ry7MkK7poILxoo", "id": {"kind": "youtube#video", "videoId": "TvwrbasgfTo"}, "snippet": {"publishedAt": "2026-04-10T10:03:00Z", "channelId": "UCjMKhUx4ozXTg9fOqfkMxXQ", "title": "From One Day Oil to Daily Blessing \ud83d\udd4a\ufe0f | \u0b92\u0bb0\u0bc1 \u0ba8\u0bbe\u0bb3\u0bcd \u0b8e\u0ba3\u0bcd\u0ba3\u0bc6\u0baf\u0bcd \u0ba4\u0bbf\u0ba9\u0bae\u0bc1\u0bae\u0bcd \u0bb5\u0bb0\u0bc1\u0bae\u0bcd \u0b9a\u0bc6\u0bb2\u0bcd\u0bb5\u0bae\u0bbe\u0b95 \u0bae\u0bbe\u0bb1\u0bbf\u0baf\u0ba4\u0bc1 \ud83d\udd25 #Jebamtv", "description": "\u0b87\u0ba8\u0bcd\u0ba4 \u0bb5\u0bc0\u0b9f\u0bbf\u0baf\u0bcb\u0bb5\u0bc8 \u0bae\u0bc1\u0bb4\u0bc1\u0bae\u0bc8\u0baf\u0bbe\u0b95 \u0baa\u0bbe\u0bb0\u0bcd\u0b95\u0bcd\u0b95 #whatsappPromisemessage #jebamtv ...", "thumbnails": {"default": {"url": "https://i.ytimg.com/vi/TvwrbasgfTo/default.jpg", "width": 120, "height": 90}, "medium": {"url": "https://i.ytimg.com/vi/TvwrbasgfTo/mqdefault.jpg", "width": 320, "height": 180}, "high": {"url": "https://i.ytimg.com/vi/TvwrbasgfTo/hqdefault.jpg", "width": 480, "height": 360}}, "channelTitle": "Jebam tv", "liveBroadcastContent": "none", "publishTime": "2026-04-10T10:03:00Z"}}, {"kind": "youtube#searchResult", "etag": "vQW7gV6dexNxvyUmDisbt91KE8U", "id": {"kind": "youtube#video", "videoId": "LSa0yAK6bAI"}, "snippet": {"publishedAt": "2026-04-10T09:45:39Z", "channelId": "UCXjFFCGFT2kNgZOS0aj-BlQ", "title": "\u0a1a\u0a32\u0a3e\u0a28 \u0a15\u0a71\u0a1f\u0a23 \u0a28\u0a42\u0a70 \u0a32\u0a48 \u0a15\u0a47 \u0a2a\u0a41\u0a32\u0a38 \u0a35\u0a3e\u0a32\u0a3f\u0a06\u0a02 \u0a28\u0a3e\u0a32 \u0a38\u0a3f\u0a71\u0a27\u0a3e \u0a39\u0a4b \u0a17\u0a3f\u0a06 \u0a28\u0a4c\u0a1c\u0a35\u0a3e\u0a28, \u0a17\u0a30\u0a2d\u0a35\u0a24\u0a40 \u0a2a\u0a24\u0a28\u0a40 \u0a26\u0a40 \u0a2a\u0a3e\u0a09\u0a02\u0a26\u0a3e \u0a30\u0a3f\u0a39\u0a3e \u0a26\u0a41\u0a39\u0a3e\u0a08", "description": "\u0a1a\u0a32\u0a3e\u0a28 \u0a15\u0a71\u0a1f\u0a23 \u0a28\u0a42\u0a70 \u0a32\u0a48 \u0a15\u0a47 \u0a2a\u0a41\u0a32\u0a38 \u0a35\u0a3e\u0a32\u0a3f\u0a06\u0a02 \u0a28\u0a3e\u0a32 \u0a38\u0a3f\u0a71\u0a27\u0a3e \u0a39\u0a4b \u0a17\u0a3f\u0a06 \u0a28\u0a4c\u0a1c\u0a35\u0a3e\u0a28, \u0a17\u0a30\u0a2d\u0a35\u0a24\u0a40 \u0a2a\u0a24\u0a28\u0a40 ...", "thumbnails": {"default": {"url": "https://i.ytimg.com/vi/LSa0yAK6bAI/default.jpg", "width": 120, "height": 90}, "medium": {"url": "https://i.ytimg.com/vi/LSa0yAK6bAI/mqdefault.jpg", "width": 320, "height": 180}, "high": {"url": "https://i.ytimg.com/vi/LSa0yAK6bAI/hqdefault.jpg", "width": 480, "height": 360}}, "channelTitle": "Star News Punjabi Tv", "liveBroadcastContent": "none", "publishTime": "2026-04-10T09:45:39Z"}}, {"kind": "youtube#searchResult", "etag": "dzuRnzMUcH4rcazAdk9BJD9ueF0", "id": {"kind": "youtube#video", "videoId": "4YgIB61RZp8"}, "snippet": {"publishedAt": "2026-04-10T09:19:25Z", "channelId": "UCV6_YQ2oaypS2oZB5MoRabg", "title": "2026 Toyota Camry LE at Toyota of Montgomery | AL", "description": "2026 Toyota Camry LE VIN: 4T1DAACKXTU293853 Toyota of Montgomery is located at 911 Eastern Blvd, Montgomery, ...", "thumbnails": {"default": {"url": "https://i.ytimg.com/vi/4YgIB61RZp8/default.jpg", "width": 120, "height": 90}, "medium": {"url": "https://i.ytimg.com/vi/4YgIB61RZp8/mqdefault.jpg", "width": 320, "height": 180}, "high": {"url": "https://i.ytimg.com/vi/4YgIB61RZp8/hqdefault.jpg", "width": 480, "height": 360}}, "channelTitle": "Toyota of Montgomery", "liveBroadcastContent": "none", "publishTime": "2026-04-10T09:19:25Z"}}, {"kind": "youtube#searchResult", "etag": "JMMg0FAFvxU41Phbih0yZUIauqA", "id": {"kind": "youtube#video", "videoId": "4NMn0HuuNT8"}, "snippet": {"publishedAt": "2026-04-10T09:00:13Z", "channelId": "UC-uwbsd_jgdvpEXHu7QBZRQ", "title": "\ud83d\ude8c\ud83d\udca8 \u09ee\u09e6+ \u09b8\u09cd\u09aa\u09bf\u09a1\u09c7 \u09b2\u09cb\u0995\u09be\u09b2 \u09ac\u09be\u09b8! \u098f\u09b0\u09be \u0995\u09bf \u09aa\u09be\u0997\u09b2 \u09a8\u09be\u0995\u09bf? \ud83d\ude21", "description": "\u09b2\u09cb\u0995\u09be\u09b2 \u09ac\u09be\u09b8 \u09ee\u09e6+ \u09b8\u09cd\u09aa\u09bf\u09a1\u09c7 \u099a\u09b2\u099b\u09c7\u2014\u09af\u09c7 \u09ac\u09be\u09b8\u0997\u09c1\u09b2\u09cb \u098f\u0987 \u0997\u09a4\u09bf\u09b0 \u099c\u09a8\u09cd\u09af \u09ae\u09cb\u099f\u09c7\u0993 \u09ab\u09bf\u099f \u09a8\u09be! \u098f\u09ae\u09a8 ...", "thumbnails": {"default": {"url": "https://i.ytimg.com/vi/4NMn0HuuNT8/default.jpg", "width": 120, "height": 90}, "medium": {"url": "https://i.ytimg.com/vi/4NMn0HuuNT8/mqdefault.jpg", "width": 320, "height": 180}, "high": {"url": "https://i.ytimg.com/vi/4NMn0HuuNT8/hqdefault.jpg", "width": 480, "height": 360}}, "channelTitle": "Ride with Soul", "liveBroadcastContent": "none", "publishTime": "2026-04-10T09:00:13Z"}}, {"kind": "youtube#searchResult", "etag": "AwR_65Fmxul-YdTWbRmJyHMc91o", "id": {"kind": "youtube#video", "videoId": "BwbHQJwqRjo"}, "snippet": {"publishedAt": "2026-04-10T05:45:28Z", "channelId": "UCZWReTJWv1HFKqTS4bKUZ2Q", "title": "Morning Bulletin: \u0935\u093f\u0915\u094d\u0930\u092e\u093e\u0926\u093f\u0924\u094d\u092f \u0915\u093e \u091c\u092f\u0930\u093e\u092e \u092a\u0930 \u092c\u0921\u093c\u093e \u0939\u092e\u0932\u093e -\u090a\u0928\u093e \u092e\u0947\u0902 \u0926\u0947\u0939 \u0935\u094d\u092f\u093e\u092a\u093e\u0930 \u0930\u0948\u0915\u0947\u091f \u0915\u093e \u092d\u0902\u0921\u093e\u092b\u094b\u0921\u093c", "description": "\u0939\u093f\u092e\u0915\u0947\u092f\u0930 \u092f\u094b\u091c\u0928\u093e \u092e\u0947\u0902 \u092c\u0921\u093c\u0947 \u092c\u0926\u0932\u093e\u0935 - \u0938\u093f\u0930\u092e\u094c\u0930 \u092e\u0947\u0902 \u0915\u093e\u0930 \u0939\u093e\u0926\u0938\u0947 \u092e\u0947\u0902 \u092e\u094c\u0924-\u0915\u0941\u0932\u094d\u0932\u0942 ...", "thumbnails": {"default": {"url": "https://i.ytimg.com/vi/BwbHQJwqRjo/default.jpg", "width": 120, "height": 90}, "medium": {"url": "https://i.ytimg.com/vi/BwbHQJwqRjo/mqdefault.jpg", "width": 320, "height": 180}, "high": {"url": "https://i.ytimg.com/vi/BwbHQJwqRjo/hqdefault.jpg", "width": 480, "height": 360}}, "channelTitle": "Anant Gyaan Himachal", "liveBroadcastContent": "none", "publishTime": "2026-04-10T05:45:28Z"}}, {"kind": "youtube#searchResult", "etag": "TX0TYuxdyh5njr6Jxx0-ZcG6dc8", "id": {"kind": "youtube#video", "videoId": "znpB-XUYjOE"}, "snippet": {"publishedAt": "2026-04-10T08:01:12Z", "channelId": "UCgA_griZWGKjZITLAiZGMQg", "title": "\u4e00\u6708\u649e\u4e03\u6b21\uff0c\u52a0\u585e\u53f8\u6a5f\u592a\u96e3\u4e86 #\u884c\u8f66\u8bb0\u5f55\u4eea\uff0c\u8f66\u7978\u73b0\u573a\uff0c\u52a0\u585e\uff0c\u9a6c\u8def\u6740\u624b\uff0c\u8fdd\u7ae0", "description": "\u4e00\u6708\u649e\u4e03\u6b21\uff0c\u52a0\u585e\u53f8\u6a5f\u592a\u96e3\u4e86\u9a6c\u8def\u8f66\u7978\u4e00\u6708\u649e\u4e03\u6b21\uff0c\u52a0\u585e\u5fc5\u906d\u62a5\u5e94Cutting in lane crashes 7 times in a month \u6a5f\u8eca\u5927\u795e\u65e5\u5e38\u8dd1\u5c71\uff0c ...", "thumbnails": {"default": {"url": "https://i.ytimg.com/vi/znpB-XUYjOE/default.jpg", "width": 120, "height": 90}, "medium": {"url": "https://i.ytimg.com/vi/znpB-XUYjOE/mqdefault.jpg", "width": 320, "height": 180}, "high": {"url": "https://i.ytimg.com/vi/znpB-XUYjOE/hqdefault.jpg", "width": 480, "height": 360}}, "channelTitle": "\u5df4\u9435\u7684\u8eca", "liveBroadcastContent": "none", "publishTime": "2026-04-10T08:01:12Z"}}, {"kind": "youtube#searchResult", "etag": "u3z4tyr3-6ylZrdKZ3galKP3Eck", "id": {"kind": "youtube#video", "videoId": "nokMGhcyWu0"}, "snippet": {"publishedAt": "2026-04-10T08:17:11Z", "channelId": "UCOqWkbnM-sQQ9ze_gcYnMrQ", "title": "India\u2019s first seaplane operator Skyhop completes successful test flight at Rishikesh\u2019s Ganga Barrage", "description": "India's first seaplane operator Skyhop has successfully completed a test flight at the Ganga Barrage in Rishikesh, marking a key ...", "thumbnails": {"default": {"url": "https://i.ytimg.com/vi/nokMGhcyWu0/default.jpg", "width": 120, "height": 90}, "medium": {"url": "https://i.ytimg.com/vi/nokMGhcyWu0/mqdefault.jpg", "width": 320, "height": 180}, "high": {"url": "https://i.ytimg.com/vi/nokMGhcyWu0/hqdefault.jpg", "width": 480, "height": 360}}, "channelTitle": "Thebluehillmail", "liveBroadcastContent": "none", "publishTime": "2026-04-10T08:17:11Z"}}, {"kind": "youtube#searchResult", "etag": "bJ4gXvGV6y8gVQNOdojz-qSSRAk", "id": {"kind": "youtube#video", "videoId": "JA7g2lrhwh4"}, "snippet": {"publishedAt": "2026-04-10T08:22:27Z", "channelId": "UC3HCgv00fpvPBsoZZ3Al80Q", "title": "Hotel Bliss - Jorhat | Jorhat, India | Hotel Review \ud83c\udfe8", "description": "Hotel Bliss - Jorhat Booking details: ...", "thumbnails": {"default": {"url": "https://i.ytimg.com/vi/JA7g2lrhwh4/default.jpg", "width": 120, "height": 90}, "medium": {"url": "https://i.ytimg.com/vi/JA7g2lrhwh4/mqdefault.jpg", "width": 320, "height": 180}, "high": {"url": "https://i.ytimg.com/vi/JA7g2lrhwh4/hqdefault.jpg", "width": 480, "height": 360}}, "channelTitle": "India Hotel Reviews", "liveBroadcastContent": "none", "publishTime": "2026-04-10T08:22:27Z"}}, {"kind": "youtube#searchResult", "etag": "n3xnJd4y2y4fYQu9TalzYC3E2sA", "id": {"kind": "youtube#video", "videoId": "d3m_2dUbENc"}, "snippet": {"publishedAt": "2026-04-10T06:44:12Z", "channelId": "UCwhRj-65CKKtjMFMAQ1LacA", "title": "A Dog Appears Out of Nowhere\u2026 What Happens Next Is Incredible!#animals #Dog", "description": "A heartwarming moment that restores faith in humanity! \u2764\ufe0f In this video, a dog suddenly appears on a busy highway, creating a ...", "thumbnails": {"default": {"url": "https://i.ytimg.com/vi/d3m_2dUbENc/default.jpg", "width": 120, "height": 90}, "medium": {"url": "https://i.ytimg.com/vi/d3m_2dUbENc/mqdefault.jpg", "width": 320, "height": 180}, "high": {"url": "https://i.ytimg.com/vi/d3m_2dUbENc/hqdefault.jpg", "width": 480, "height": 360}}, "channelTitle": "HonourCapture", "liveBroadcastContent": "none", "publishTime": "2026-04-10T06:44:12Z"}}, {"kind": "youtube#searchResult", "etag": "CLUtdZgfjDMOY8zHzorJHX0ofnE", "id": {"kind": "youtube#video", "videoId": "dnHsAhr5KNw"}, "snippet": {"publishedAt": "2026-04-10T07:54:17Z", "channelId": "UCBbJP51XSONEtvXStxbj8qA", "title": "\u0905\u0932\u0940\u0917\u0922\u093c \u0915\u0947 \u0925\u093e\u0928\u093e \u0915\u094d\u0935\u093e\u0930\u094d\u0938\u0940 \u0915\u094d\u0937\u0947\u0924\u094d\u0930 \u0915\u0940 \u0930\u093f\u092f\u093e\u091c \u0915\u0949\u0932\u094b\u0928\u0940 \u092e\u0947\u0902 \u0938\u0921\u093c\u0915 \u0939\u093e\u0926\u0938\u0947 \u0915\u093e \u0935\u0940\u0921\u093f\u092f\u094b \u0938\u094b\u0936\u0932 \u092e\u0940\u0921\u093f\u092f\u093e \u092a\u0930 \u0935\u093e\u092f\u0930\u0932\u0964", "description": "\u092c\u094d\u0930\u0947\u0915\u093f\u0902\u0917 \u0928\u094d\u092f\u0942\u091c\u093c | \u0905\u0932\u0940\u0917\u0922 \u0905\u0932\u0940\u0917\u0922\u093c \u0915\u0947 \u0925\u093e\u0928\u093e \u0915\u094d\u0935\u093e\u0930\u094d\u0938\u0940 \u0915\u094d\u0937\u0947\u0924\u094d\u0930 \u0915\u0940 \u0930\u093f\u092f\u093e\u091c ...", "thumbnails": {"default": {"url": "https://i.ytimg.com/vi/dnHsAhr5KNw/default.jpg", "width": 120, "height": 90}, "medium": {"url": "https://i.ytimg.com/vi/dnHsAhr5KNw/mqdefault.jpg", "width": 320, "height": 180}, "high": {"url": "https://i.ytimg.com/vi/dnHsAhr5KNw/hqdefault.jpg", "width": 480, "height": 360}}, "channelTitle": "MORNING CITY DIGITAL NEWS", "liveBroadcastContent": "none", "publishTime": "2026-04-10T07:54:17Z"}}, {"kind": "youtube#searchResult", "etag": "DbsgojzXK3d0YvJ0l2ErnfCKE0g", "id": {"kind": "youtube#video", "videoId": "HEfr80CMd3Y"}, "snippet": {"publishedAt": "2026-04-10T06:37:52Z", "channelId": "UCCoRA3EOkQ35FLX8CK5MSRA", "title": "10 April Se Toll Ke Naye Niyam! \ud83d\udee3\ufe0f | FASTag Update &amp; New Toll Rules 2026", "description": "Savdhaan! 10 April se National Highways aur Expressways par toll tax ke niyam badalne ja rahe hain. Agar aapki gaadi par ...", "thumbnails": {"default": {"url": "https://i.ytimg.com/vi/HEfr80CMd3Y/default.jpg", "width": 120, "height": 90}, "medium": {"url": "https://i.ytimg.com/vi/HEfr80CMd3Y/mqdefault.jpg", "width": 320, "height": 180}, "high": {"url": "https://i.ytimg.com/vi/HEfr80CMd3Y/hqdefault.jpg", "width": 480, "height": 360}}, "channelTitle": "@SKINA@", "liveBroadcastContent": "none", "publishTime": "2026-04-10T06:37:52Z"}}, {"kind": "youtube#searchResult", "etag": "bveOS3N2hiClntTgD-LdhIu4aRk", "id": {"kind": "youtube#video", "videoId": "anfTJ6TQHmg"}, "snippet": {"publishedAt": "2026-04-10T06:07:01Z", "channelId": "UCtNRbKV_tOe_Te_CdRNuFTw", "title": "Siddha Eden Lakeville | Pollution-Free Lakeside Living | BT Road Landmark", "description": "Siddha Eden Lakeville | Pollution-Free Lakeside Living | BT Road Landmark Discover a breath of fresh air at North Kolkata's ...", "thumbnails": {"default": {"url": "https://i.ytimg.com/vi/anfTJ6TQHmg/default.jpg", "width": 120, "height": 90}, "medium": {"url": "https://i.ytimg.com/vi/anfTJ6TQHmg/mqdefault.jpg", "width": 320, "height": 180}, "high": {"url": "https://i.ytimg.com/vi/anfTJ6TQHmg/hqdefault.jpg", "width": 480, "height": 360}}, "channelTitle": "KEY ESTATES", "liveBroadcastContent": "none", "publishTime": "2026-04-10T06:07:01Z"}}, {"kind": "youtube#searchResult", "etag": "hLZWnLle5kfwhNfA5o8x65pndZU", "id": {"kind": "youtube#video", "videoId": "y51xHt7586I"}, "snippet": {"publishedAt": "2026-04-10T06:45:40Z", "channelId": "UCkBEaGzSjXem5ywmzSvHcEw", "title": "\u0917\u093e\u091c\u0940\u092a\u0941\u0930 \u092c\u0938 \u0939\u093e\u0926\u0938\u093e 35 \u0918\u093e\u092f\u0932, 2 \u0915\u0940 \u092e\u094c#\u0924  \u092a\u0924\u094d\u0925\u0930\u092c\u093e\u091c\u0940 \u0915\u0940 \u0905\u092b\u0935\u093e\u0939 \u0928\u093f\u0915\u0932\u0940 \u091d\u0942\u0920\u0940  CCTV \u092e\u0947\u0902 \u0938\u091a \u0906\u092f\u093e \u0938\u093e\u092e\u0928\u0947#news", "description": "\u0917\u093e\u091c\u0940\u092a\u0941\u0930 \u092c\u0938 \u0939\u093e\u0926\u0938\u093e: 35 \u0918\u093e\u092f\u0932, 2 \u0915\u0940 \u092e\u094c\u0924 | \u092a\u0924\u094d\u0925\u0930\u092c\u093e\u091c\u0940 \u0915\u0940 \u0905\u092b\u0935\u093e\u0939 \u0928\u093f\u0915\u0932\u0940 \u091d\u0942\u0920\u0940 | CCTV ...", "thumbnails": {"default": {"url": "https://i.ytimg.com/vi/y51xHt7586I/default.jpg", "width": 120, "height": 90}, "medium": {"url": "https://i.ytimg.com/vi/y51xHt7586I/mqdefault.jpg", "width": 320, "height": 180}, "high": {"url": "https://i.ytimg.com/vi/y51xHt7586I/hqdefault.jpg", "width": 480, "height": 360}}, "channelTitle": "Bedhadak Sach", "liveBroadcastContent": "none", "publishTime": "2026-04-10T06:45:40Z"}}, {"kind": "youtube#searchResult", "etag": "CF3NkmmJMw_1WVScQTtBovnvCxI", "id": {"kind": "youtube#video", "videoId": "ZcAOpe_lrSY"}, "snippet": {"publishedAt": "2026-04-10T05:54:00Z", "channelId": "UCs_aQcpq_TuSyE6fALO1rrA", "title": "#GhazipurAccident\u200b \u0917\u093e\u091c\u0940\u092a\u0941\u0930 \u092e\u0947\u0902 \u092c\u0938 \u092a\u0932\u091f\u0940 2 \u092e\u0939\u093f\u0932\u093e\u0913\u0902 \u0915\u0940 \u092e\u094c\u0924 20 \u0938\u0947 \u091c\u094d\u092f\u093e\u0926\u093e \u0918\u093e\u092f\u0932 #BusAccident\u200b #upnews #UP", "description": "\u092c\u094d\u0930\u0947\u0915\u093f\u0902\u0917 \u0928\u094d\u092f\u0942\u091c\u093c - \u0917\u094b\u0930\u0916\u092a\u0941\u0930-\u0935\u093e\u0930\u093e\u0923\u0938\u0940 \u0939\u093e\u0908\u0935\u0947 \u092a\u0930 \u0917\u093e\u091c\u0940\u092a\u0941\u0930 \u0915\u0947 \u0928\u0902\u0926\u0917\u0902\u091c \u0925\u093e\u0928\u093e ...", "thumbnails": {"default": {"url": "https://i.ytimg.com/vi/ZcAOpe_lrSY/default.jpg", "width": 120, "height": 90}, "medium": {"url": "https://i.ytimg.com/vi/ZcAOpe_lrSY/mqdefault.jpg", "width": 320, "height": 180}, "high": {"url": "https://i.ytimg.com/vi/ZcAOpe_lrSY/hqdefault.jpg", "width": 480, "height": 360}}, "channelTitle": "Reporting Monu ghz", "liveBroadcastContent": "none", "publishTime": "2026-04-10T05:54:00Z"}}, {"kind": "youtube#searchResult", "etag": "2Iue5VELAbrIFxaEzgoB9vErofs", "id": {"kind": "youtube#video", "videoId": "mwrFfM7obXo"}, "snippet": {"publishedAt": "2026-04-10T10:30:37Z", "channelId": "UCYGUa8R1MPyK6rF9Ep2NJeQ", "title": "2026 Hyundai Creta Summer Edition Launched \ud83d\udd25 at \u20b912.05 Lakh! (New Features &amp; Full Price) \ud83d\ude31\ud83d\udd25 #creta", "description": "2026 Hyundai Creta Summer Edition Launched at \u20b912.05 Lakh! (New Features & Full Price) Hyundai India has just turned up the ...", "thumbnails": {"default": {"url": "https://i.ytimg.com/vi/mwrFfM7obXo/default.jpg", "width": 120, "height": 90}, "medium": {"url": "https://i.ytimg.com/vi/mwrFfM7obXo/mqdefault.jpg", "width": 320, "height": 180}, "high": {"url": "https://i.ytimg.com/vi/mwrFfM7obXo/hqdefault.jpg", "width": 480, "height": 360}}, "channelTitle": "MG AUTOS", "liveBroadcastContent": "none", "publishTime": "2026-04-10T10:30:37Z"}}, {"kind": "youtube#searchResult", "etag": "6pKNJANcazJ7Go7xin6MKhFjsvU", "id": {"kind": "youtube#video", "videoId": "9VgzGmXn_oE"}, "snippet": {"publishedAt": "2026-04-10T08:26:59Z", "channelId": "UCD634s4shEapL_Ds49Hk8SQ", "title": "Skoda Kylaq Top Model Review \ud83d\udd25 Full Features, Price &amp; Mileage 2026", "description": "Skoda Kylaq Top Model Review Full Features, Price & Mileage 2026 Skoda Kylaq Top Model Review Full Features, Price ...", "thumbnails": {"default": {"url": "https://i.ytimg.com/vi/9VgzGmXn_oE/default.jpg", "width": 120, "height": 90}, "medium": {"url": "https://i.ytimg.com/vi/9VgzGmXn_oE/mqdefault.jpg", "width": 320, "height": 180}, "high": {"url": "https://i.ytimg.com/vi/9VgzGmXn_oE/hqdefault.jpg", "width": 480, "height": 360}}, "channelTitle": "A TO Z REVIEW ", "liveBroadcastContent": "none", "publishTime": "2026-04-10T08:26:59Z"}}, {"kind": "youtube#searchResult", "etag": "BrWRiF-qYoP4OMSGCPc4rvrhxjs", "id": {"kind": "youtube#video", "videoId": "eHu-I4X93GM"}, "snippet": {"publishedAt": "2026-04-10T06:46:40Z", "channelId": "UC4SmwegXMajDo2eqcUhBEaw", "title": "Balod News : \u092c\u093e\u0932\u094b\u0926 \u092e\u0947\u0902 \u0939\u0947\u0932\u092e\u0947\u091f \u0905\u092d\u093f\u092f\u093e\u0928 \u0924\u0947\u091c, \u092a\u0941\u0932\u093f\u0938 \u0938\u0916\u094d\u0924", "description": "\u092c\u093e\u0932\u094b\u0926 \u092e\u0947\u0902 \u092f\u093e\u0924\u093e\u092f\u093e\u0924 \u092a\u0941\u0932\u093f\u0938 \u0926\u094d\u0935\u093e\u0930\u093e \u0939\u0947\u0932\u092e\u0947\u091f \u0938\u0902\u0915\u0932\u094d\u092a \u0905\u092d\u093f\u092f\u093e\u0928 \u091a\u0932\u093e\u0915\u0930 \u0938\u0921\u093c\u0915 ...", "thumbnails": {"default": {"url": "https://i.ytimg.com/vi/eHu-I4X93GM/default.jpg", "width": 120, "height": 90}, "medium": {"url": "https://i.ytimg.com/vi/eHu-I4X93GM/mqdefault.jpg", "width": 320, "height": 180}, "high": {"url": "https://i.ytimg.com/vi/eHu-I4X93GM/hqdefault.jpg", "width": 480, "height": 360}}, "channelTitle": "UNA MPCG", "liveBroadcastContent": "none", "publishTime": "2026-04-10T06:46:40Z"}}, {"kind": "youtube#searchResult", "etag": "wlrHnlBldKciKn3taeNQ44TUA8g", "id": {"kind": "youtube#video", "videoId": "BSjyKRkTvVE"}, "snippet": {"publishedAt": "2026-04-10T13:00:00Z", "channelId": "UCvZnlMETbjhnZUvParirbXQ", "title": "\u5168\u56fd\u4e0b\u96ea\uff0c\u9752\u5c9b\u4e0b\u96e8\ud83d\ude02\ud83d\ude02\uff0c\u4e1c\u5317\u5927\u54e5\u6765\u9752\u5c9b\u8d4f\u96e8\u5427\ud83d\ude02\ud83d\ude02", "description": "Welcome to Damaner Tire Fix! Whether you're stuck on the road or just need a quick tire fix at home, we've got you covered.", "thumbnails": {"default": {"url": "https://i.ytimg.com/vi/BSjyKRkTvVE/default.jpg", "width": 120, "height": 90}, "medium": {"url": "https://i.ytimg.com/vi/BSjyKRkTvVE/mqdefault.jpg", "width": 320, "height": 180}, "high": {"url": "https://i.ytimg.com/vi/BSjyKRkTvVE/hqdefault.jpg", "width": 480, "height": 360}}, "channelTitle": "Damaner Tire Fix", "liveBroadcastContent": "none", "publishTime": "2026-04-10T13:00:00Z"}}, {"kind": "youtube#searchResult", "etag": "lK6B5CEexDCu4TbWdOjPu1gDP0Y", "id": {"kind": "youtube#video", "videoId": "jRr0N3W4Heo"}, "snippet": {"publishedAt": "2026-04-10T07:54:35Z", "channelId": "UCri5Ju8uqRxIAwIQp8FsBYQ", "title": "\u0938\u0940\u092e\u093e\u0902\u0924 \u0917\u093e\u0902\u0935 \u0917\u0947\u0902\u0935\u093e\u0932\u0940 \u092a\u0939\u0941\u0902\u091a\u0940\u0902 DM, \u0938\u092e\u0938\u094d\u092f\u093e\u0913\u0902 \u092a\u0930 \u090f\u0915\u094d\u0936\u0928 #parvatsankalpnews #pushkarsinghdhami", "description": "\u091f\u093f\u0939\u0930\u0940 \u0915\u0940 \u091c\u093f\u0932\u093e\u0927\u093f\u0915\u093e\u0930\u0940 \u0928\u093f\u0924\u093f\u0915\u093e \u0916\u0902\u0921\u0947\u0932\u0935\u093e\u0932 \u0928\u0947 \u0918\u0928\u0938\u093e\u0932\u0940 \u0935\u093f\u0927\u093e\u0928\u0938\u092d\u093e \u0915\u094d\u0937\u0947\u0924\u094d\u0930 \u0915\u0947 ...", "thumbnails": {"default": {"url": "https://i.ytimg.com/vi/jRr0N3W4Heo/default.jpg", "width": 120, "height": 90}, "medium": {"url": "https://i.ytimg.com/vi/jRr0N3W4Heo/mqdefault.jpg", "width": 320, "height": 180}, "high": {"url": "https://i.ytimg.com/vi/jRr0N3W4Heo/hqdefault.jpg", "width": 480, "height": 360}}, "channelTitle": "Parvat Sankalp ", "liveBroadcastContent": "none", "publishTime": "2026-04-10T07:54:35Z"}}, {"kind": "youtube#searchResult", "etag": "nl2azJmnHYiwZ8qh_j02ecdIsd4", "id": {"kind": "youtube#video", "videoId": "Y_etknTM3Ls"}, "snippet": {"publishedAt": "2026-04-10T09:07:48Z", "channelId": "UCJ3v6zVB1rrdRQcG_gSWKRA", "title": "Overtake \u092c\u0928\u093e \u091c\u093e\u0928\u0932\u0947\u0935\u093e! \u092c\u093e\u0907\u0915 \u0938\u0935\u093e\u0930 \u092c\u093e\u0932-\u092c\u093e\u0932 \u092c\u091a\u093e, \u0926\u0947\u0916\u0947\u0902 \u0916\u094c\u092b\u0928\u093e\u0915 \u0935\u0940\u0921\u093f\u092f\u094b", "description": "\u0938\u0921\u093c\u0915 \u092a\u0930 \u0924\u0947\u091c \u0930\u092b\u094d\u0924\u093e\u0930 \u0915\u092d\u0940 \u092d\u0940 \u091c\u093e\u0928\u0932\u0947\u0935\u093e \u0938\u093e\u092c\u093f\u0924 \u0939\u094b \u0938\u0915\u0924\u0940 \u0939\u0948\u0964 \u0907\u0938 \u0935\u093e\u092f\u0930\u0932 \u0935\u0940\u0921\u093f\u092f\u094b ...", "thumbnails": {"default": {"url": "https://i.ytimg.com/vi/Y_etknTM3Ls/default.jpg", "width": 120, "height": 90}, "medium": {"url": "https://i.ytimg.com/vi/Y_etknTM3Ls/mqdefault.jpg", "width": 320, "height": 180}, "high": {"url": "https://i.ytimg.com/vi/Y_etknTM3Ls/hqdefault.jpg", "width": 480, "height": 360}}, "channelTitle": "Lead News Today", "liveBroadcastContent": "none", "publishTime": "2026-04-10T09:07:48Z"}}, {"kind": "youtube#searchResult", "etag": "7NDoQMmUubBVv-FIRKY5QSz-7Mk", "id": {"kind": "youtube#video", "videoId": "_pBrM0da2mM"}, "snippet": {"publishedAt": "2026-04-10T09:35:13Z", "channelId": "UCx8wl0oCY4Ktojmj0nF8RGw", "title": "\u0c39\u0c46\u0c32\u0c4d\u0c2e\u0c46\u0c1f\u0c4d \u0c32\u0c47\u0c15\u0c2a\u0c4b\u0c24\u0c47 \u0c2b\u0c48\u0c28\u0c4d \u0c0e\u0c02\u0c24 ? | What is the fine for riding without a helmet ? \ud83e\ude96 | @BRKLawyer", "description": "\u0c39\u0c46\u0c32\u0c4d\u0c2e\u0c46\u0c1f\u0c4d \u0c32\u0c47\u0c15\u0c2a\u0c4b\u0c24\u0c47 \u0c2b\u0c48\u0c28\u0c4d \u0c0e\u0c02\u0c24 ? | What is the fine for riding without a helmet ? | \u2068@BRKLawyer\u2069 ...", "thumbnails": {"default": {"url": "https://i.ytimg.com/vi/_pBrM0da2mM/default.jpg", "width": 120, "height": 90}, "medium": {"url": "https://i.ytimg.com/vi/_pBrM0da2mM/mqdefault.jpg", "width": 320, "height": 180}, "high": {"url": "https://i.ytimg.com/vi/_pBrM0da2mM/hqdefault.jpg", "width": 480, "height": 360}}, "channelTitle": "BRK Lawyer", "liveBroadcastContent": "none", "publishTime": "2026-04-10T09:35:13Z"}}, {"kind": "youtube#searchResult", "etag": "X98Cs9E__sbEv_ZOOB4TAOVfF7I", "id": {"kind": "youtube#video", "videoId": "FuCY_lJkYxw"}, "snippet": {"publishedAt": "2026-04-10T07:05:15Z", "channelId": "UCPTtP4c_XV0TMndEV_DHkZg", "title": "\u0915\u093e\u0902\u0915\u0947\u0930 \u092e\u0947\u0902 \u092d\u0940\u0937\u0923 \u0938\u0921\u093c\u0915 \u0939\u093e\u0926\u0938\u093e \u090f\u0915 \u0939\u0940 \u092a\u0930\u093f\u0935\u093e\u0930 \u0915\u0947 6 \u0932\u094b\u0917\u094b\u0902 \u0915\u0940 \u092e\u094c\u0924 #kanker #accidentnews", "description": "hindinews #viralnews #awaazindiatv #kanker #accidentnews #roadaccident #speedkills #chattisgarhnews #roadsafety ...", "thumbnails": {"default": {"url": "https://i.ytimg.com/vi/FuCY_lJkYxw/default.jpg", "width": 120, "height": 90}, "medium": {"url": "https://i.ytimg.com/vi/FuCY_lJkYxw/mqdefault.jpg", "width": 320, "height": 180}, "high": {"url": "https://i.ytimg.com/vi/FuCY_lJkYxw/hqdefault.jpg", "width": 480, "height": 360}}, "channelTitle": "Awaaz India Hindi", "liveBroadcastContent": "none", "publishTime": "2026-04-10T07:05:15Z"}}, {"kind": "youtube#searchResult", "etag": "pctBDKG3pjeMfXmernZ_ZDkRzjM", "id": {"kind": "youtube#video", "videoId": "A0pK-vW6gnA"}, "snippet": {"publishedAt": "2026-04-10T08:19:06Z", "channelId": "UCVJEq2s3wdOX2i9kTnqBs5w", "title": "#accident #roadaccident #todaynews #youtubeshorts", "description": "accident #roadaccident #cctvfootage #accidentvideo #viralvideo #trendingnow #shorts #youtubeshorts #viralshorts #explorepage ...", "thumbnails": {"default": {"url": "https://i.ytimg.com/vi/A0pK-vW6gnA/default.jpg", "width": 120, "height": 90}, "medium": {"url": "https://i.ytimg.com/vi/A0pK-vW6gnA/mqdefault.jpg", "width": 320, "height": 180}, "high": {"url": "https://i.ytimg.com/vi/A0pK-vW6gnA/hqdefault.jpg", "width": 480, "height": 360}}, "channelTitle": "@Viveekyt-vlog", "liveBroadcastContent": "none", "publishTime": "2026-04-10T08:19:06Z"}}, {"kind": "youtube#searchResult", "etag": "PNWgWqE05Shh2-gEI8GBqEQb27s", "id": {"kind": "youtube#video", "videoId": "Dc2E3RgCMPU"}, "snippet": {"publishedAt": "2026-04-10T05:53:32Z", "channelId": "UCX-zOrr3UT8qxi2Qm8KP_DQ", "title": "Why public roads aren&#39;t racetracks.", "description": "Description: This video serves as a sobering reminder of how quickly things can go wrong on the road. High-speed maneuvers on ...", "thumbnails": {"default": {"url": "https://i.ytimg.com/vi/Dc2E3RgCMPU/default.jpg", "width": 120, "height": 90}, "medium": {"url": "https://i.ytimg.com/vi/Dc2E3RgCMPU/mqdefault.jpg", "width": 320, "height": 180}, "high": {"url": "https://i.ytimg.com/vi/Dc2E3RgCMPU/hqdefault.jpg", "width": 480, "height": 360}}, "channelTitle": "Cryptic Feed", "liveBroadcastContent": "none", "publishTime": "2026-04-10T05:53:32Z"}}, {"kind": "youtube#searchResult", "etag": "Izu7wLgokpL8DYBVvI6zfBbJPZE", "id": {"kind": "youtube#video", "videoId": "xIYEQsAqvFE"}, "snippet": {"publishedAt": "2026-04-10T09:47:08Z", "channelId": "UC39MTy8ZFSqK6ykIT630E0w", "title": "\u0915\u0941\u0924\u094d\u0924\u094b\u0902 \u0928\u0947 \u0926\u094c\u095c\u093e\u092f\u093e, \u0915\u093e\u0930 \u0938\u0947 \u091f\u0915\u0930\u093e\u0908 \u0938\u094d\u0915\u0942\u091f\u0940! \u0930\u094b\u0902\u0917\u091f\u0947 \u0916\u095c\u0947 \u0915\u0930 \u0926\u0947\u0917\u093e \u092f\u0939 CCTV \u092b\u0941\u091f\u0947\u091c! #viralvideo \u0964", "description": "\u0915\u0941\u0924\u094d\u0924\u094b\u0902 \u0928\u0947 \u0926\u094c\u0921\u093c\u093e\u092f\u093e, \u0915\u093e\u0930 \u0938\u0947 \u091f\u0915\u0930\u093e\u0908 \u0938\u094d\u0915\u0942\u091f\u0940! \u0930\u094b\u0902\u0917\u091f\u0947 \u0916\u0921\u093c\u0947 \u0915\u0930 \u0926\u0947\u0917\u093e \u092f\u0939 CCTV ...", "thumbnails": {"default": {"url": "https://i.ytimg.com/vi/xIYEQsAqvFE/default.jpg", "width": 120, "height": 90}, "medium": {"url": "https://i.ytimg.com/vi/xIYEQsAqvFE/mqdefault.jpg", "width": 320, "height": 180}, "high": {"url": "https://i.ytimg.com/vi/xIYEQsAqvFE/hqdefault.jpg", "width": 480, "height": 360}}, "channelTitle": "Khas khabar UP ", "liveBroadcastContent": "none", "publishTime": "2026-04-10T09:47:08Z"}}], "metadata": {"batch_id": "yt_1775837743", "keyword": "road safety", "timestamp": "2026-04-10T16:16:02.431559Z", "source": "youtube_v3_search"}}